qrfast-0.1.0.dist-info/METADATA
qrfast-0.1.0.dist-info/WHEEL
qrfast/__init__.py
qrfast/__init__.pyi
qrfast/py.typed
qrfast/qrfast.abi3.so
qrfast-0.1.0.dist-info/RECORD
