Metadata-Version: 2.4
Name: qrfast
Version: 0.1.0
Classifier: Development Status :: 4 - Beta
Classifier: Intended Audience :: Developers
Classifier: License :: OSI Approved :: MIT License
Classifier: Programming Language :: Rust
Classifier: Programming Language :: Python :: Implementation :: CPython
Classifier: Programming Language :: Python :: Implementation :: PyPy
Classifier: Programming Language :: Python :: 3
Classifier: Programming Language :: Python :: 3.8
Classifier: Programming Language :: Python :: 3.9
Classifier: Programming Language :: Python :: 3.10
Classifier: Programming Language :: Python :: 3.11
Classifier: Programming Language :: Python :: 3.12
Classifier: Topic :: Software Development :: Libraries :: Python Modules
Classifier: Topic :: Multimedia :: Graphics
Summary: Fast QR code generation and decoding library powered by Rust
Keywords: qr,qrcode,barcode,rust,fast
Author-email: Jamal Saied <jsaied99@gmail.com>
License: MIT
Requires-Python: >=3.8
Project-URL: Homepage, https://github.com/jsaied99/qrfast
Project-URL: Repository, https://github.com/jsaied99/qrfast
Project-URL: Issues, https://github.com/jsaied99/qrfast/issues
